fabric_digitalocean/__init__.py
fabric_digitalocean/decorators.py
fabric_digitalocean/tests/__init__.py
fabric_digitalocean/tests/test_decorators.py
fabric_digitalocean-0.1.dist-info/DESCRIPTION.rst
fabric_digitalocean-0.1.dist-info/METADATA
fabric_digitalocean-0.1.dist-info/RECORD
fabric_digitalocean-0.1.dist-info/WHEEL
fabric_digitalocean-0.1.dist-info/metadata.json
fabric_digitalocean-0.1.dist-info/top_level.txt
