Metadata-Version: 2.0
Name: fabric-digitalocean
Version: 0.1
Summary: A collection of fabric tools for working with DigitalOcean
Home-page: https://github.com/andrewsomething/fabric-digitalocean
Author: Andrew Starr-Bochicchio
Author-email: a.starr.b@gmail.com
License: BSD-2-Clause
Download-URL: https://github.com/andrewsomething/fabric-digitalocean/releases
Platform: UNKNOWN
Requires-Dist: fabric
Requires-Dist: python-digitalocean
Provides-Extra: test
Requires-Dist: coverage; extra == 'test'
Requires-Dist: nose; extra == 'test'
Requires-Dist: responses; extra == 'test'
